DolphinMath/__init__.py
DolphinMath/numbers.py
DolphinMath/prime.py
DolphinMath/sequences.py
DolphinMath/series.py
DolphinMath/stats.py
dolphinmath-0.0.2.dist-info/METADATA
dolphinmath-0.0.2.dist-info/WHEEL
dolphinmath-0.0.2.dist-info/top_level.txt
dolphinmath-0.0.2.dist-info/RECORD
