Metadata-Version: 2.4
Name: dolphinmath
Version: 0.0.2
Summary: Simple math helper library made by a student
Author: Peddakotla Karthikeya
License: MIT
Project-URL: Homepage, https://pypi.org/project/dolphinmath/
Requires-Python: >=3.8
